jgp_report_components/__init__.py
jgp_report_components/resources/img/logo_jgp.png
jgp_report_components/template/__init__.py
jgp_report_components/template/letter_portrait.py
jgp_report_components-0.0.1.dist-info/LICENSE
jgp_report_components-0.0.1.dist-info/METADATA
jgp_report_components-0.0.1.dist-info/WHEEL
jgp_report_components-0.0.1.dist-info/top_level.txt
jgp_report_components-0.0.1.dist-info/RECORD
